chevir_kartalol/__init__.py
chevir_kartalol/evaluation.py
chevir_kartalol/transformer.py
chevir_kartalol-0.2.dist-info/METADATA
chevir_kartalol-0.2.dist-info/WHEEL
chevir_kartalol-0.2.dist-info/top_level.txt
chevir_kartalol-0.2.dist-info/RECORD
