Metadata-Version: 2.1
Name: chevir-kartalol
Version: 0.2
Summary: A translator from English to Azerbiajani(Arabic Script) package
Home-page: https://github.com/jalilnkh/
Author: Jalil Nourmohammadi Kartal
Author-email: jalil.nourmohammadi89@gmail.com
License: MIT
Platform: UNKNOWN
Classifier: Programming Language :: Python :: 3
Classifier: License :: OSI Approved :: MIT License
Classifier: Operating System :: OS Independent
Requires-Python: >=3.10
